ff_hidden_species2pg/__init__.py
ff_hidden_species2pg/helpers.py
ff_hidden_species2pg/main.py
ff_hidden_species2pg-0.1.0.dist-info/METADATA
ff_hidden_species2pg-0.1.0.dist-info/WHEEL
ff_hidden_species2pg-0.1.0.dist-info/entry_points.txt
ff_hidden_species2pg-0.1.0.dist-info/RECORD
