Metadata-Version: 2.1
Name: ff-hidden-species2pg
Version: 0.1.0
Summary: 
Author: Fred C
Author-email: fcloitre@dbwildlife.info
Requires-Python: >=3.10,<4.0
Classifier: Programming Language :: Python :: 3
Classifier: Programming Language :: Python :: 3.10
Classifier: Programming Language :: Python :: 3.11
Classifier: Programming Language :: Python :: 3.12
Requires-Dist: beautifulsoup4 (>=4.12.3,<5.0.0)
Requires-Dist: click (>=8.1.7,<9.0.0)
Requires-Dist: psycopg2-binary (>=2.9.9,<3.0.0)
Requires-Dist: requests (>=2.31.0,<3.0.0)
Requires-Dist: types-beautifulsoup4 (>=4.12.0.20240229,<5.0.0.0)
